{"Items":[{"id":"m3","name":"Caesar Salad","image":"images/food3.jpg","description":"Romanin and Hot milk pound to moke and Round of","price":60,"quantity":4},{"id":"m2","name":"Remon Delta","image":"images/food2.jpg","description":"Romanin and Hot milk pound to moke and Round of","price":80,"quantity":2},{"id":"m5","name":"Caesar Salad","image":"images/food5.jpg","description":"Romanin and Hot milk pound to moke and Round of","price":43,"quantity":1}],"customer":{"fullName":"yogesh","email":"beztech24@gmail.com","street":"Surat","postal-code":"39007","city":"dfgfd"}}